RH56DFTP/RH56DFTP_TCP.py
RH56DFTP/RH56DFTP_TCP.pyi
RH56DFTP/RH56DFTP_base.py
RH56DFTP/RH56DFTP_base.pyi
RH56DFTP/__init__.py
Register/__init__.py
Register/RegisterBuild/RegisterFactory.py
Register/RegisterBuild/__init__.py
Register/RegisterBuild/RegisterCreationStrategy/FTPRegisterStrategy.py
Register/RegisterBuild/RegisterCreationStrategy/RegisterCreationStrategy.py
Register/RegisterKey/__init__.py
Register/RegisterKey/build_keys.py
Register/RegisterKey/ftp_registers_keys.py
Register/RegisterSet/RegisterBase.py
Register/RegisterSet/Register_FTP.py
Register/RegisterSet/__init__.py
Register/config/configFTP/ftp_registers.py
Register/config/configFTP/__pycache__/ftp_registers.cpython-312.pyc
plusml_rh56dftp-0.1.7.dist-info/licenses/LICENSE
plusml_rh56dftp-0.1.7.dist-info/METADATA
plusml_rh56dftp-0.1.7.dist-info/WHEEL
plusml_rh56dftp-0.1.7.dist-info/top_level.txt
plusml_rh56dftp-0.1.7.dist-info/RECORD
