Metadata-Version: 2.4
Name: plusml-rh56dftp
Version: 0.1.7
Summary: A Python library for communicating with RH56DFTP devices (tactile hand)
Home-page: https://github.com/plus-m-r/RH56DFTP_teach
Author: plus-m-r
Author-email: 
Project-URL: Homepage, https://github.com/plus-m-r/RH56DFTP_teach
Project-URL: Repository, https://github.com/plus-m-r/RH56DFTP_teach
Classifier: Programming Language :: Python :: 3
Classifier: License :: OSI Approved :: MIT License
Classifier: Operating System :: OS Independent
Requires-Python: >=3.7
License-File: LICENSE
Requires-Dist: pymodbus==3.11.3
Dynamic: home-page
Dynamic: license-file
Dynamic: requires-python
